md_server/__init__.py
md_server/__main__.py
md_server/app.py
md_server/controllers.py
md_server/models.py
md_server/core/__init__.py
md_server/core/browser.py
md_server/core/config.py
md_server/core/converter.py
md_server/core/detection.py
md_server/core/errors.py
md_server/core/factories.py
md_server/core/validation.py
md_server/mcp/__init__.py
md_server/mcp/errors.py
md_server/mcp/handlers.py
md_server/mcp/models.py
md_server/mcp/server.py
md_server/mcp/tools.py
md_server/metadata/__init__.py
md_server/metadata/extractor.py
md_server/middleware/__init__.py
md_server/middleware/auth.py
md_server/sdk/__init__.py
md_server/sdk/converter.py
md_server/sdk/models.py
md_server/sdk/remote.py
md_server/security/__init__.py
md_server/security/url_validator.py
md_server-0.1.8.dist-info/licenses/LICENSE
md_server-0.1.8.dist-info/METADATA
md_server-0.1.8.dist-info/WHEEL
md_server-0.1.8.dist-info/entry_points.txt
md_server-0.1.8.dist-info/top_level.txt
md_server-0.1.8.dist-info/RECORD
