Metadata-Version: 2.4
Name: md-server
Version: 0.1.8
Summary: HTTP API and MCP server for converting documents, web pages, and media to markdown
Author-email: Peter Etelej <peter@etelej.com>
Maintainer-email: Peter Etelej <peter@etelej.com>
License-Expression: MIT
Project-URL: Homepage, https://github.com/peteretelej/md-server
Project-URL: Repository, https://github.com/peteretelej/md-server.git
Project-URL: Issues, https://github.com/peteretelej/md-server/issues
Project-URL: Documentation, https://github.com/peteretelej/md-server#readme
Keywords: markdown,document-conversion,api,server,mcp,model-context-protocol,pdf,docx
Classifier: Development Status :: 5 - Production/Stable
Classifier: Intended Audience :: Developers
Classifier: Topic :: Internet :: WWW/HTTP :: HTTP Servers
Classifier: Topic :: Text Processing :: Markup
Classifier: Topic :: Software Development :: Libraries :: Python Modules
Classifier: Programming Language :: Python :: 3
Classifier: Programming Language :: Python :: 3.10
Classifier: Programming Language :: Python :: 3.11
Classifier: Programming Language :: Python :: 3.12
Classifier: Operating System :: OS Independent
Requires-Python: >=3.10
License-File: LICENSE
Requires-Dist: litestar[standard]>=2.0.0
Requires-Dist: markitdown[all]>=0.0.1
Requires-Dist: pydantic>=2.11.7
Requires-Dist: pydantic-settings>=2.10.1
Requires-Dist: crawl4ai>=0.7.0
Requires-Dist: click!=8.2.2
Requires-Dist: psutil>=7.0.0
Requires-Dist: tiktoken>=0.5.0
Requires-Dist: langdetect>=1.0.9
Requires-Dist: mcp>=1.0.0
Dynamic: license-file
